dm_reverb_nightly-0.15.0.dev20240214.data/headers/checkpoint.proto
dm_reverb_nightly-0.15.0.dev20240214.data/headers/patterns.proto
dm_reverb_nightly-0.15.0.dev20240214.data/headers/reverb_config.proto
dm_reverb_nightly-0.15.0.dev20240214.data/headers/schema.proto
reverb/__init__.py
reverb/client.py
reverb/errors.py
reverb/item_selectors.py
reverb/libcheckpoint_cc_proto.so
reverb/libpatterns_cc_proto.so
reverb/libpybind.so
reverb/libreverb_service_cc_proto.so
reverb/libschema_cc_proto.so
reverb/pattern_dataset.py
reverb/pybind.py
reverb/rate_limiters.py
reverb/replay_sample.py
reverb/reverb_types.py
reverb/server.py
reverb/structured_writer.py
reverb/tf_client.py
reverb/timestep_dataset.py
reverb/trajectory_dataset.py
reverb/trajectory_writer.py
reverb/cc/__init__.py
reverb/cc/patterns_pb2.py
reverb/cc/schema_pb2.py
reverb/cc/checkpointing/__init__.py
reverb/cc/checkpointing/checkpoint_pb2.py
reverb/cc/ops/__init__.py
reverb/cc/ops/gen_reverb_ops.py
reverb/cc/ops/libgen_reverb_ops_gen_op.so
reverb/pip_package/__init__.py
reverb/platform/__init__.py
reverb/platform/checkpointers_lib.py
reverb/platform/default/__init__.py
reverb/platform/default/checkpointers.py
reverb/platform/default/ensure_tf_install.py
reverb/platform/default/load_op_library.py
reverb/platform/default/server_main_command_line_args.py
reverb/server_executable/__init__.py
reverb/server_executable/reverb_config_pb2.py
reverb/server_executable/server_from_proto.py
reverb/server_executable/server_main.py
dm_reverb_nightly-0.15.0.dev20240214.dist-info/LICENSE
dm_reverb_nightly-0.15.0.dev20240214.dist-info/METADATA
dm_reverb_nightly-0.15.0.dev20240214.dist-info/WHEEL
dm_reverb_nightly-0.15.0.dev20240214.dist-info/entry_points.txt
dm_reverb_nightly-0.15.0.dev20240214.dist-info/top_level.txt
dm_reverb_nightly-0.15.0.dev20240214.dist-info/RECORD
